plover_jaws/__init__.py
plover_jaws-1.0a7.dist-info/METADATA
plover_jaws-1.0a7.dist-info/WHEEL
plover_jaws-1.0a7.dist-info/entry_points.txt
plover_jaws-1.0a7.dist-info/top_level.txt
plover_jaws-1.0a7.dist-info/zip-safe
plover_jaws-1.0a7.dist-info/RECORD
