Metadata-Version: 2.1
Name: plover-jaws
Version: 1.0a7
Summary: Provides spoken feedback via the JAWS screen reader
Home-page: UNKNOWN
Author: Glen Gordon
Author-email: ggordon@vispero.com
License: GNU General Public License v2 (GPLv2)
Keywords: plover plover_plugin
Platform: UNKNOWN
Classifier: License :: OSI Approved :: GNU General Public License v2 or later (GPLv2+)
Classifier: Development Status :: 3 - Alpha
Classifier: Environment :: Plugins
Classifier: Intended Audience :: End Users/Desktop
Classifier: Operating System :: Microsoft :: Windows
Classifier: Programming Language :: Python :: 3.6
Requires-Dist: plover (>=4.0.dev6)
Requires-Dist: pywin32 (>=223)
